README.md
setup.py
rileytest69/__init__.py
rileytest69/classes.py
rileytest69/client.py
rileytest69/errors.py
rileytest69.egg-info/PKG-INFO
rileytest69.egg-info/SOURCES.txt
rileytest69.egg-info/dependency_links.txt
rileytest69.egg-info/requires.txt
rileytest69.egg-info/top_level.txt