Metadata-Version: 2.1
Name: rileytest69
Version: 5.0
Summary: An easy to use Python Wrapper for the AlexFlipnote API
Home-page: https://github.com/Soheab/Alexflipnote.py
Author: Soheab_
License: MIT
Download-URL: https://github.com/Soheab/alexflipnote.py/archive/v5.0.tar.gz
Project-URL: Discord, https://discord.gg/DpxkY3x
Project-URL: Source, https://github.com/Soheab/alexflipnote.py
Project-URL: Documentation, https://github.com/Soheab/alexflipnote.py/blob/master/docs.md
Project-URL: Issue tracker, https://github.com/Soheab/alexflipnote.py/issues
Keywords: alexflipnote,discord,api,wrapper,memes,image,discord.py
Platform: UNKNOWN
Requires-Python: >=3.6
